{
    "Cole": [
        {
            "action": "IN",
            "time": "2025-05-23T12:11:33.949033"
        },
        {
            "action": "OUT",
            "time": "2025-05-23T13:16:02.152257"
        },
        {
            "action": "IN",
            "time": "2025-05-23T13:16:16.052608"
        },
        {
            "action": "OUT",
            "time": "2025-05-23T14:07:14.673778"
        },
        {
            "action": "IN",
            "time": "2025-05-23T15:57:09.525573"
        },
        {
            "action": "OUT",
            "time": "2025-05-23T17:22:51.047835"
        },
        {
            "action": "IN",
            "time": "2025-05-23T17:28:08.197997"
        },
        {
            "action": "OUT",
            "time": "2025-05-23T17:38:12.074786"
        }
    ]
}